{
  "Kael Vorn": {
    "name": "Kael Vorn",
    "location": "unknown",
    "health": 100,
    "mood": "neutral",
    "goals": [],
    "inventory": [],
    "tags": {},
    "updated_at": "2026-05-11T20:01:59.643080"
  },
  "Syln": {
    "name": "Syln",
    "location": "unknown",
    "health": 100,
    "mood": "neutral",
    "goals": [],
    "inventory": [],
    "tags": {},
    "updated_at": "2026-05-11T20:01:59.643083"
  },
  "Grandcarver Oth": {
    "name": "Grandcarver Oth",
    "location": "unknown",
    "health": 100,
    "mood": "neutral",
    "goals": [],
    "inventory": [],
    "tags": {},
    "updated_at": "2026-05-11T20:01:59.643086"
  },
  "Null": {
    "name": "Null",
    "location": "unknown",
    "health": 100,
    "mood": "neutral",
    "goals": [],
    "inventory": [],
    "tags": {},
    "updated_at": "2026-05-11T20:01:59.643087"
  },
  "Verra Cinder": {
    "name": "Verra Cinder",
    "location": "unknown",
    "health": 100,
    "mood": "neutral",
    "goals": [],
    "inventory": [],
    "tags": {},
    "updated_at": "2026-05-11T20:01:59.643089"
  },
  "Brek-of-Three-Depths": {
    "name": "Brek-of-Three-Depths",
    "location": "unknown",
    "health": 100,
    "mood": "neutral",
    "goals": [],
    "inventory": [],
    "tags": {},
    "updated_at": "2026-05-11T20:01:59.643091"
  }
}